econutils/__init__.py
econutils-0.1.4.dist-info/licenses/LICENSE
econutils-0.1.4.dist-info/METADATA
econutils-0.1.4.dist-info/WHEEL
econutils-0.1.4.dist-info/top_level.txt
econutils-0.1.4.dist-info/RECORD
