Metadata-Version: 2.4
Name: econutils
Version: 0.1.4
Summary: utility function for econsystem
Author-email: Tetragram <tetragramdev@gmail.com>
License: MIT
Requires-Python: >=3.7
License-File: LICENSE
Dynamic: license-file
